Metadata-Version: 2.1
Name: Konversi-suhu-niaa
Version: 0.0.1
Summary: A small example package
Home-page: https://gitlab.com/kurnia_endah/pelatihan_bmkg.git
Author: Kurnia Endah Komalasari
Author-email: Kurnia Endah Komalasari <kurniaendah.ks@gmail.com>
Classifier: Programming Language :: Python :: 3
Classifier: License :: OSI Approved :: MIT License
Classifier: Operating System :: OS Independent
Requires-Python: >=3.7
License-File: LICENSE.txt
